__init__.py
wildkit/__init__.py
wildkit/common/__init__.py
wildkit/common/client.py
wildkit/content/__init__.py
wildkit/content/__main__.py
wildkit/content/common.py
wildkit/content/configurator.py
wildkit/content/configurator_categories.py
wildkit/content/configurator_characteristics.py
wildkit/content/configurator_colors.py
wildkit/content/const.py
wildkit/content/upload.py
wildkit/usecases/__init__.py
wildkit/usecases/__main__.py
wildkit-0.0.1.dist-info/METADATA
wildkit-0.0.1.dist-info/WHEEL
wildkit-0.0.1.dist-info/top_level.txt
wildkit-0.0.1.dist-info/RECORD
